README.md
TARBSengine.py
__init__.py
create_issue.py
setup.cfg
setup.py
test.py
TARBSengine.egg-info/PKG-INFO
TARBSengine.egg-info/SOURCES.txt
TARBSengine.egg-info/dependency_links.txt
TARBSengine.egg-info/top_level.txt