Metadata-Version: 2.1
Name: TARBSengine
Version: 1.0.0.2
Summary: Totally Accurate RPG Battle Simulation Engine
Home-page: https://github.com/tman540/T.A.R.B.S.-Engine
Author: Steven Tautonico
Author-email: stautonico@gmail.com
License: MIT
Platform: UNKNOWN
Classifier: Development Status :: 3 - Alpha
Classifier: Intended Audience :: Developers
Classifier: License :: OSI Approved :: MIT License
Classifier: Programming Language :: Python :: 3.6
